<?xml version="1.0" encoding="utf-8"?>
<data xmlns:xsi="http://www.w3.org/2001/XMLSchema-instance">
    <dtype_two xmlns:xsi="http://www.w3.org/2001/XMLSchema-instance">
        <dtype_twoType_Fee value="123" value2="456"/>
        <p1>p1_data_2</p1>
        <p2>p1_data_2</p2>
        <p3>p1_data_2</p3>
        <p4>p1_data_2</p4>
        <p5>p1_data_2</p5>
    </dtype_two>
    <dtype_one>
        <p1>p1_data_1</p1>
        <p2>p1_data_1</p2>
        <p3>p1_data_1</p3>
        <p4>p1_data_1</p4>
        <p5>p1_data_1</p5>
    </dtype_one>
    <dtype_two>
        <dtype_twoType_Fee value="789" value2="456"/>
        <p1>p1_data_2</p1>
        <p2>p1_data_2</p2>
        <p3>p1_data_2</p3>
        <p4>p1_data_2</p4>
        <p5>p1_data_2</p5>
    </dtype_two>
    <WS>
        <dtype_three>
            <p1>p1_data_3</p1>
            <p2>p1_data_3</p2>
            <p3>p1_data_3</p3>
            <p4>p1_data_3</p4>
            <p5>p1_data_3</p5>
        </dtype_three>
    </WS>
    <dtype_two>
        <dtype_twoType_Fee value="23423424" value2="24234"/>
        <p1>p1_data_2</p1>
        <p2>p1_data_2</p2>
        <p3>p1_data_2</p3>
        <p4>p1_data_2</p4>
        <p5>p1_data_2</p5>
    </dtype_two>
</data>